{
  "id": "christoph_1768312226",
  "user": "christoph",
  "created_by": "christoph",
  "module_id": "A1",
  "goal": "Auto: A1 – Rink IQ & Rollenverständnis",
  "confidence": 3,
  "focus": null,
  "session_method": "live_watch",
  "drill_id": "A1_D2",
  "state": "COMPLETED",
  "current_phase": "POST",
  "created_at": "2026-01-13T14:50:26.145764",
  "drills": [
    {
      "id": "A1_D2",
      "title": "Shift Marker → 2-Sekunden-Scan (Center)",
      "drill_type": "shift_tracker",
      "description": "Serienbeobachtung. Einsatz: Live oder Re-Live. Dauer: 8–12 Shifts.",
      "didactics": {
        "explanation": "Du trainierst hier eine feste Beobachtungsroutine:\n\n1) Ein Ereignis (Shift Marker) tritt auf.\n2) Du schaust exakt 2 Sekunden auf den Center.\n3) Du notierst nur seine Position – ohne Bewertung.\n\nEs geht nicht um richtig oder falsch, sondern um Wiederholung und Mustererkennung.",
        "observation_guide": {
          "what_to_watch": [
            "Wo befindet sich der Center ~2 Sekunden nach dem Marker?",
            "Ist er eher absichernd, verbindend oder jagend unterwegs?"
          ],
          "how_to_decide": [
            "Marker erkennen → innerlich zählen → Position wählen",
            "Wenn unsicher: das wählen, was am nächsten dran ist",
            "Nicht erklären, nicht rechtfertigen"
          ],
          "ignore": [
            "Erfolg oder Misserfolg der Aktion",
            "Torchancen oder technische Details",
            "Emotionale Bewertung"
          ]
        },
        "shift_marker_explanation": "Ein Shift Marker ist nur ein Auslöser für deine Beobachtung.\n\nTypische Marker:\n• Puckverlust\n• misslungener Pass\n• Zweikampf an der Bande\n• Zonenwechsel\n\nDer Marker selbst wird **nicht** bewertet.",
        "learning_hint": "Je neutraler du bleibst, desto klarer werden die Muster."
      },
      "config": {
        "shift_count": 10,
        "questions": [
          {
            "key": "shift_marker",
            "type": "radio",
            "label": "Was war der Shift Marker?",
            "options": [
              "Puckverlust",
              "misslungener Pass",
              "Zweikampf an der Bande",
              "Zonenwechsel",
              "sonstiger Moment"
            ]
          },
          {
            "key": "center_position",
            "type": "radio",
            "label": "Center-Position ~2 Sekunden nach dem Marker:",
            "options": [
              "tief (unter dem Spiel / Absicherung)",
              "mittel (Middle / verbindend)",
              "hoch (vor dem Spiel / jagt)"
            ]
          }
        ]
      }
    }
  ],
  "progress": {
    "current_drill_index": 0,
    "completed_drills": []
  },
  "checkins": [
    {
      "phase": "PRE",
      "answers": {},
      "feedback": "Weiter zur nächsten Phase",
      "next_task": "Nächste Phase vorbereiten",
      "timestamp": "2026-01-13T14:50:33.799764"
    },
    {
      "phase": "P1",
      "answers": {},
      "feedback": "Weiter zur nächsten Phase",
      "next_task": "Nächste Phase vorbereiten",
      "timestamp": "2026-01-13T14:50:51.663188"
    },
    {
      "phase": "P2",
      "answers": {},
      "feedback": "Weiter zur nächsten Phase",
      "next_task": "Nächste Phase vorbereiten",
      "timestamp": "2026-01-13T14:50:53.207225"
    },
    {
      "phase": "P3",
      "answers": {},
      "feedback": "Weiter zur nächsten Phase",
      "next_task": "Nächste Phase vorbereiten",
      "timestamp": "2026-01-13T14:50:53.971089"
    },
    {
      "phase": "POST",
      "answers": {},
      "feedback": "Gut gemacht!",
      "next_task": "Bereite nächste Phase vor",
      "timestamp": "2026-01-13T14:50:56.732934"
    }
  ],
  "drafts": {},
  "post": {
    "summary": "",
    "unclear": "",
    "next_module": "",
    "helpfulness": 0,
    "completed_at": "2026-01-13T14:50:56.771470"
  },
  "game_info": {
    "league": "DEL",
    "team_home": "ERC Ingolstadt",
    "team_away": "Augsburger Panther",
    "date": "2026-01-13T13:50:26.100Z"
  }
}